curriculum_analysis/__init__.py
curriculum_analysis/analysis.py
curriculum_analysis/config.cfg.default
curriculum_analysis/corpus.py
curriculum_analysis/csv_exporter.py
curriculum_analysis/js_exporter.py
curriculum_analysis/json_exporter.py
curriculum_analysis/keywords.py
curriculum_analysis/keywords.txt
curriculum_analysis/main.py
curriculum_analysis/txt_parser.py
curriculum_analysis/html/data.js
curriculum_analysis/html/index.html
curriculum_analysis/html/index.js
curriculum_analysis/html/module.html
curriculum_analysis/html/module.js
curriculum_analysis/top-level/index.html
curriculum_analysis/top-level/index.js
curriculum_analysis/top-level/pages.js
curriculum_analysis/top-level/style.css
curriculum_analysis-0.2.12.dist-info/METADATA
curriculum_analysis-0.2.12.dist-info/WHEEL
curriculum_analysis-0.2.12.dist-info/entry_points.txt
curriculum_analysis-0.2.12.dist-info/licenses/LICENCE
curriculum_analysis-0.2.12.dist-info/RECORD
