Metadata-Version: 2.4
Name: curriculum_analysis
Version: 0.2.12
Summary: A simple tool for analysing DMU module and programme specifications with respect to provided keywords.
Project-URL: Homepage, https://github.com/IESD/curriculumAnalysis
Project-URL: Bug Tracker, https://github.com/IESD/curriculumAnalysis/issues
Author: Tom Harrison
Author-email: Graeme Stuart <gstuart@dmu.ac.uk>
License-File: LICENCE
Classifier: License :: OSI Approved :: MIT License
Classifier: Operating System :: OS Independent
Classifier: Programming Language :: Python :: 3
Requires-Python: >=3.10
Requires-Dist: nltk>=3.8.1
